odoo/addons/shopinvader_invoice/README.rst
odoo/addons/shopinvader_invoice/__init__.py
odoo/addons/shopinvader_invoice/__manifest__.py
odoo/addons/shopinvader_invoice/readme/CONTRIBUTORS.rst
odoo/addons/shopinvader_invoice/readme/DESCRIPTION.rst
odoo/addons/shopinvader_invoice/services/__init__.py
odoo/addons/shopinvader_invoice/services/invoice.py
odoo/addons/shopinvader_invoice/static/description/index.html
odoo/addons/shopinvader_invoice/tests/__init__.py
odoo/addons/shopinvader_invoice/tests/test_invoice_service.py
odoo12_addon_shopinvader_invoice-12.0.1.2.1.dist-info/METADATA
odoo12_addon_shopinvader_invoice-12.0.1.2.1.dist-info/WHEEL
odoo12_addon_shopinvader_invoice-12.0.1.2.1.dist-info/top_level.txt
odoo12_addon_shopinvader_invoice-12.0.1.2.1.dist-info/RECORD
