Metadata-Version: 2.1
Name: odoo12-addon-shopinvader-invoice
Version: 12.0.1.2.1
Summary: Shopinvader Invoice module
Home-page: https://shopinvader.com
Author: ACSONE SA/NV
License: AGPL-3
Platform: UNKNOWN
Classifier: Programming Language :: Python
Classifier: Framework :: Odoo
Classifier: License :: OSI Approved :: GNU Affero General Public License v3
Requires-Python: >=3.5
Requires-Dist: odoo12-addon-shopinvader
Requires-Dist: odoo (<12.1dev,>=12.0a)
